Workbook

Sheet Team Roles
A1: Name | B1: Role | C1: Responsibilities | D1: Status
A2: Stefano | B2: CEO / Founder | C2: Vision, strategy, sales, client relationships, final decisions | D2: Active
A3: Mac | B3: COO / Co-Founder | C3: Technical execution, operations, tool setup, AI configuration, problem-solving | D3: Active

Sheet 2-Week Launch Plan
A1: Day | B1: Date Range | C1: Task | D1: Owner | E1: Status
A2: Day 1 | B2: Week 1 | C2: Set up GoHighLevel account & CRM pipeline | D2: Mac
A3: Day 1 | C3: Finalize FNDI branding, website copy & pricing | D3: Stefano
A4: Day 2 | C4: Configure Synthflow AI voice agent | D4: Mac
A5: Day 2 | C5: Build target client list (50 local businesses) | D5: Stefano
A6: Day 3 | C6: Connect Twilio phone number + test calls | D6: Mac
A7: Day 3 | C7: Write outreach scripts (cold call + email) | D7: Stefano
A8: Day 4 | C8: Set up GoHighLevel automations & follow-ups | D8: Mac
A9: Day 4 | C9: Create demo video / screen recording | D9: Stefano
A10: Day 5 | C10: Full end-to-end test: call → AI → CRM → follow-up | D10: Both
A11: Day 5 | C11: Fix any bugs, polish demo flow | D11: Mac
A12: Day 6 | B12: Week 2 | C12: Start outreach — call/email first 10 businesses | D12: Stefano
A13: Day 6 | C13: Monitor AI calls, tune responses | D13: Mac
A14: Day 7 | C14: Follow up on Day 6 leads, book demos | D14: Stefano
A15: Day 7 | C15: Build client onboarding checklist | D15: Mac
A16: Day 8 | C16: Run 2-3 live demos with interested prospects | D16: Stefano
A17: Day 8 | C17: Customize AI agent per prospect industry | D17: Mac
A18: Day 9 | C18: Outreach to next 15 businesses | D18: Stefano
A19: Day 9 | C19: Set up client dashboard in GoHighLevel | D19: Mac
A20: Day 10 | C20: Close first 1-2 paying clients | D20: Stefano
A21: Day 10 | C21: Onboard first clients, deploy their AI agents | D21: Mac
A22: Day 11-14 | C22: Continue outreach cycle — aim for 5 clients | D22: Stefano
A23: Day 11-14 | C23: Support live clients, gather feedback, iterate | D23: Mac

Sheet Tool Costs
A1: FNDI — TOOL STACK & MONTHLY COSTS
A3: Tool | B3: What It Does | C3: Plan | D3: Monthly Cost | E3: Priority
A4: GoHighLevel | B4: CRM, SMS, email, pipelines, booking | C4: Agency Starter | D4: 97 | E4: 🔴 Must Have
A5: Synthflow AI | B5: Voice agents for phone calls | C5: Starter | D5: 29 | E5: 🔴 Must Have
A6: Twilio | B6: Phone numbers & call routing | C6: Pay-as-you-go | D6: 20 | E6: 🔴 Must Have
A7: OpenAI API | B7: GPT for chatbot & voice AI brain | C7: Pay-as-you-go | D7: 20 | E7: 🔴 Must Have
A8: Chatbase | B8: Website chatbot builder | C8: Free / Hobby | D8: 0 | E8: 🟡 Important
A9: Calendly | B9: Booking & scheduling | C9: Free | D9: 0 | E9: 🟢 Already Set Up
A10: Canva | B10: Proposals, graphics, social media | C10: Free | D10: 0 | E10: 🟢 Already Set Up
A11: Make.com | B11: Automation workflows | C11: Free (1000 ops) | D11: 0 | E11: 🟡 Important
A12: Zapier | B12: Backup automation tool | C12: Free (100 tasks) | D12: 0 | E12: 🟡 Nice to Have
A13: ManyChat | B13: Instagram DM automation | C13: Free (up to 1000) | D13: 0 | E13: 🟡 Important
A14: Gmail Workspace | B14: Professional email | C14: Business Starter | D14: 7 | E14: 🟡 Nice to Have
A15: Vercel | B15: Website hosting | C15: Free (Hobby) | D15: 0 | E15: 🟢 Already Set Up
A16: TOTAL MONTHLY COST (to start) | D16: =SUM(D4:D15) -> 173

Sheet Revenue Targets
A1: FNDI — REVENUE & PROFIT PROJECTIONS
A3: Metric | B3: Month 1 | C3: Month 2 | D3: Month 3 | E3: Month 6 | F3: Month 12
A4: Clients (Starter $297) | B4: 2 | C4: 4 | D4: 6 | E4: 10 | F4: 15
A5: Clients (Growth $697) | B5: 1 | C5: 2 | D5: 4 | E5: 8 | F5: 12
A6: Clients (Dominate $997) | B6: 0 | C6: 1 | D6: 2 | E6: 4 | F6: 6
A7: Total Clients | B7: =B4+B5+B6 -> 3 | C7: =C4+C5+C6 -> 7 | D7: =D4+D5+D6 -> 12 | E7: =E4+E5+E6 -> 22 | F7: =F4+F5+F6 -> 33
A9: Monthly Recurring Revenue | B9: =(B4*297)+(B5*697)+(B6*997) -> 1291 | C9: =(C4*297)+(C5*697)+(C6*997) -> 3579 | D9: =(D4*297)+(D5*697)+(D6*997) -> 6564 | E9: =(E4*297)+(E5*697)+(E6*997) -> 12534 | F9: =(F4*297)+(F5*697)+(F6*997) -> 18801
A10: Setup Fees (one-time) | B10: =(B4*500)+(B5*1000)+(B6*1500) -> 2000 | C10: =(C4*500)+(C5*1000)+(C6*1500) -> 5500 | D10: =(D4*500)+(D5*1000)+(D6*1500) -> 10000 | E10: =(E4*500)+(E5*1000)+(E6*1500) -> 19000 | F10: =(F4*500)+(F5*1000)+(F6*1500) -> 28500
A11: Tool Costs | B11: ='Tool Costs'!D16 -> 173 | C11: ='Tool Costs'!D16 -> 173 | D11: ='Tool Costs'!D16 -> 173 | E11: ='Tool Costs'!D16 -> 173 | F11: ='Tool Costs'!D16 -> 173
A12: Victor Commission (25% MRR) | B12: =B9*0.25 -> 322.75 | C12: =C9*0.25 -> 894.75 | D12: =D9*0.25 -> 1641 | E12: =E9*0.25 -> 3133.5 | F12: =F9*0.25 -> 4700.25
A14: NET MONTHLY PROFIT | B14: =B9-B11-B12 -> 795.25 | C14: =C9-C11-C12 -> 2511.25 | D14: =D9-D11-D12 -> 4750 | E14: =E9-E11-E12 -> 9227.5 | F14: =F9-F11-F12 -> 13927.75

Sheet Sales Tracker
A1: Business Name | B1: Industry | C1: Contact Method | D1: Status | E1: Monthly Value | F1: Owner

Sheet KPIs
A1: KPI | B1: Week 1 Target | C1: Week 1 Actual | D1: Week 2 Target | E1: Week 2 Actual
A2: Outreach calls/emails (Stefano) | B2: 25 | D2: 40
A3: Demos booked (Stefano) | B3: 3 | D3: 5
A4: Demos completed | B4: 2 | D4: 4
A5: Proposals sent | B5: 1 | D5: 3
A6: Clients closed | B6: 0 | D6: 2
A7: AI agents deployed (Mac) | B7: 0 | D7: 2
A8: Monthly recurring revenue | B8: $0 | D8: $1,000+
A9: Tool stack fully tested | B9: Yes | D9: N/A
